SyBA/SyBA.py
SyBA-0.0.5.dist-info/LICENSE
SyBA-0.0.5.dist-info/METADATA
SyBA-0.0.5.dist-info/WHEEL
SyBA-0.0.5.dist-info/top_level.txt
SyBA-0.0.5.dist-info/RECORD
