Metadata-Version: 2.1
Name: SyBA
Version: 0.0.5
Summary: SyBA: a tool and database for standardizing gene names from the main bacterial pathogens causing food contamination
Home-page: https://github.com/luanrabelo/SyBA
Download-URL: https://github.com/luanrabelo/SyBA
Author: Luan Rabelo
Author-email: luanrabelo@outlook.com
Maintainer: Luan Rabelo
Maintainer-email: luanrabelo@outlook.com
License: MIT License
Keywords: SyBA Genes Bioinformatics Synonymous
Classifier: Development Status :: 5 - Production/Stable
Classifier: Intended Audience :: Science/Research
Classifier: Environment :: Web Environment
Classifier: Topic :: Scientific/Engineering :: Bio-Informatics
Classifier: License :: OSI Approved :: MIT License
Classifier: Programming Language :: Python :: 3.7
Classifier: Operating System :: Microsoft :: Windows
Classifier: Operating System :: MacOS :: MacOS X
Classifier: Operating System :: POSIX :: Linux
License-File: LICENSE
Requires-Dist: requests
Requires-Dist: pandas
Requires-Dist: numpy
